src/__init__.py
src/benchmark.py
src/simple_linear_regr.py
src/simple_linear_regr_utils.py
mle_project-0.1.2.dist-info/METADATA
mle_project-0.1.2.dist-info/WHEEL
mle_project-0.1.2.dist-info/RECORD
