Metadata-Version: 2.1
Name: mle-project
Version: 0.1.2
Summary: 
Author: an ng
Author-email: ahnguyen.work@gmail.com
Requires-Python: >=3.9,<4.0
Classifier: Programming Language :: Python :: 3
Classifier: Programming Language :: Python :: 3.9
Classifier: Programming Language :: Python :: 3.10
Classifier: Programming Language :: Python :: 3.11
Requires-Dist: matplotlib (==3.7.1)
Requires-Dist: numpy (==1.20)
Requires-Dist: scikit-learn (==1.2.2)
